{"type": "GenericCrafter", "name": "baje factory", "description": "...", "health": 135, "size": 2, "requirements": [{"item": "pivojunium", "amount": 18}, {"item": "saze", "amount": 13}, {"item": "devo", "amount": 16}], "research": "mechanical-drill", "hasPower": true, "hasItems": true, "hasLiquids": false, "craftTime": 10, "consumes": {"power": 1.0, "items": {"items": [{"item": "hasifa", "amount": 4}, {"item": "kujodo", "amount": 1}]}}, "updateEffect": "smeltsmoke", "category": "crafting", "idleSoundVolume": 0.5, "itemCapacity": 20, "outputItem": {"item": "baje", "amount": 19}}