{"type": "GenericSmelter", "name": "beqa smelter", "description": "...", "health": 100, "size": 2, "requirements": [{"item": "tiqi", "amount": 5}, {"item": "lesoxonium", "amount": 20}, {"item": "ciwy", "amount": 10}], "research": "beqa-factory", "hasPower": true, "hasItems": true, "hasLiquids": true, "craftTime": 1, "consumes": {"power": 6, "items": {"items": [{"item": "beqa", "amount": 2}]}}, "updateEffect": "smeltsmoke", "category": "crafting", "idleSoundVolume": 0.5, "liquidCapacity": 10, "itemCapacity": 10, "outputLiquid": {"liquid": "molten-beqa", "amount": 3}}