{"type": "GenericSmelter", "name": "bihu smelter", "description": "...", "health": 100, "size": 2, "requirements": [{"item": "yytiye", "amount": 17}, {"item": "sexinium", "amount": 12}, {"item": "migube", "amount": 7}], "research": "bihu-factory", "hasPower": true, "hasItems": true, "hasLiquids": true, "craftTime": 1, "consumes": {"power": 5, "items": {"items": [{"item": "bihu", "amount": 1}]}}, "updateEffect": "smeltsmoke", "category": "crafting", "idleSoundVolume": 0.5, "liquidCapacity": 10, "itemCapacity": 10, "outputLiquid": {"liquid": "molten-bihu", "amount": 9}}