{"type": "GenericCrafter", "name": "bore factory", "description": "...", "health": 556, "size": 1, "requirements": [{"item": "wadoka", "amount": 12}, {"item": "fizy", "amount": 5}, {"item": "cuba", "amount": 14}], "research": "mechanical-drill", "hasPower": true, "hasItems": true, "hasLiquids": false, "craftTime": 10, "consumes": {"power": 4.0, "items": {"items": [{"item": "faruna", "amount": 17}, {"item": "tebebe", "amount": 2}]}}, "updateEffect": "smeltsmoke", "category": "crafting", "idleSoundVolume": 0.5, "itemCapacity": 20, "outputItem": {"item": "bore", "amount": 3}}