{"type": "DoubleTurret", "name": "cafazu turret", "description": ",,,", "health": 185, "size": 4, "reload": 8, "range": 210, "innacuracy": 0, "rotatespeed": 55, "ammo": {"cafazu": {"speed": 55, "damage": 56, "bulletWidth": 10, "bulletHeight": 20, "shootEffect": "shootSmall", "smokeEffect": "shootPyraFlame", "ammoMultiplier": 1}, "pary": {"speed": 44, "damage": 39, "bulletWidth": 10, "bulletHeight": 20, "shootEffect": "shootSmall", "smokeEffect": "shootPyraFlame", "ammoMultiplier": 1}, "boretu": {"speed": 23, "damage": 32, "bulletWidth": 10, "bulletHeight": 20, "shootEffect": "shootSmall", "smokeEffect": "shootPyraFlame", "ammoMultiplier": 1}}, "requirements": [{"item": "cafazu", "amount": 1}, {"item": "fica", "amount": 15}, {"item": "fito", "amount": 30}], "category": "turret", "research": "cafazu-factory", "ammoUseEffect": "shellEjectSmall"}