{"type": "GenericSmelter", "name": "ceqo smelter", "description": "...", "health": 100, "size": 2, "requirements": [{"item": "yuqy", "amount": 6}, {"item": "tupo", "amount": 20}, {"item": "bexa", "amount": 6}], "research": "ceqo-factory", "hasPower": true, "hasItems": true, "hasLiquids": true, "craftTime": 1, "consumes": {"power": 3, "items": {"items": [{"item": "ceqo", "amount": 9}]}}, "updateEffect": "smeltsmoke", "category": "crafting", "idleSoundVolume": 0.5, "liquidCapacity": 10, "itemCapacity": 10, "outputLiquid": {"liquid": "molten-ceqo", "amount": 10}}