{"type": "GenericSmelter", "name": "cigapo smelter", "description": "...", "health": 100, "size": 2, "requirements": [{"item": "gino", "amount": 20}, {"item": "hyvyje", "amount": 4}, {"item": "pygilenium", "amount": 1}], "research": "cigapo-factory", "hasPower": true, "hasItems": true, "hasLiquids": true, "craftTime": 1, "consumes": {"power": 9, "items": {"items": [{"item": "cigapo", "amount": 6}]}}, "updateEffect": "smeltsmoke", "category": "crafting", "idleSoundVolume": 0.5, "liquidCapacity": 10, "itemCapacity": 10, "outputLiquid": {"liquid": "molten-cigapo", "amount": 10}}