{"type": "GenericCrafter", "name": "cobe factory", "description": "...", "health": 238, "size": 2, "requirements": [{"item": "wypa", "amount": 9}, {"item": "ridu", "amount": 10}, {"item": "lekewy", "amount": 19}], "research": "mechanical-drill", "hasPower": true, "hasItems": true, "hasLiquids": true, "craftTime": 10, "consumes": {"power": 6.0, "items": {"items": [{"item": "potesonium", "amount": 15}]}, "liquid": {"liquid": "molten-biny", "amount": 1}}, "updateEffect": "smeltsmoke", "category": "crafting", "idleSoundVolume": 0.5, "liquidCapacity": 10, "itemCapacity": 20, "outputItem": {"item": "cobe", "amount": 17}}