{"type": "GenericSmelter", "name": "cowi smelter", "description": "...", "health": 100, "size": 2, "requirements": [{"item": "qasy", "amount": 3}, {"item": "silicon", "amount": 19}, {"item": "wizacy", "amount": 7}], "research": "cowi-factory", "hasPower": true, "hasItems": true, "hasLiquids": true, "craftTime": 1, "consumes": {"power": 3, "items": {"items": [{"item": "cowi", "amount": 8}]}}, "updateEffect": "smeltsmoke", "category": "crafting", "idleSoundVolume": 0.5, "liquidCapacity": 10, "itemCapacity": 10, "outputLiquid": {"liquid": "molten-cowi", "amount": 4}}