{"type": "DoubleTurret", "name": "dara turret", "description": ",,,", "health": 378, "size": 4, "reload": 7, "range": 128, "innacuracy": 0, "rotatespeed": 268, "ammo": {"dara": {"speed": 34, "damage": 58, "bulletWidth": 10, "bulletHeight": 20, "shootEffect": "shootSmall", "smokeEffect": "shootPyraFlame", "ammoMultiplier": 1}, "yaxuda": {"speed": 76, "damage": 30, "bulletWidth": 10, "bulletHeight": 20, "shootEffect": "shootSmall", "smokeEffect": "shootPyraFlame", "ammoMultiplier": 1}, "wozego": {"speed": 8, "damage": 12, "bulletWidth": 10, "bulletHeight": 20, "shootEffect": "shootSmall", "smokeEffect": "shootPyraFlame", "ammoMultiplier": 1}}, "requirements": [{"item": "dara", "amount": 1}, {"item": "pavanium", "amount": 22}, {"item": "yudesinium", "amount": 24}], "category": "turret", "research": "dara-factory", "ammoUseEffect": "shellEjectSmall"}