{"type": "GenericCrafter", "name": "delo factory", "description": "...", "health": 536, "size": 2, "requirements": [{"item": "teyonium", "amount": 9}, {"item": "rukonium", "amount": 16}, {"item": "myci", "amount": 1}], "research": "mechanical-drill", "hasPower": true, "hasItems": true, "hasLiquids": false, "craftTime": 10, "consumes": {"power": 5.0, "items": {"items": [{"item": "wapalu", "amount": 9}, {"item": "jucinium", "amount": 2}]}}, "updateEffect": "smeltsmoke", "category": "crafting", "idleSoundVolume": 0.5, "itemCapacity": 20, "outputItem": {"item": "delo", "amount": 20}}