{"type": "GenericCrafter", "name": "divimenium factory", "description": "...", "health": 156, "size": 3, "requirements": [{"item": "tufi", "amount": 7}, {"item": "xebili", "amount": 19}, {"item": "juge", "amount": 20}], "research": "mechanical-drill", "hasPower": true, "hasItems": true, "hasLiquids": false, "craftTime": 10, "consumes": {"power": 7.0, "items": {"items": [{"item": "pehy", "amount": 8}, {"item": "gifu", "amount": 1}]}}, "updateEffect": "smeltsmoke", "category": "crafting", "idleSoundVolume": 0.5, "itemCapacity": 20, "outputItem": {"item": "divimenium", "amount": 18}}