{"type": "GenericSmelter", "name": "dowoca smelter", "description": "...", "health": 100, "size": 2, "requirements": [{"item": "dakyse", "amount": 3}, {"item": "veco", "amount": 15}, {"item": "lapydy", "amount": 5}], "research": "dowoca-factory", "hasPower": true, "hasItems": true, "hasLiquids": true, "craftTime": 1, "consumes": {"power": 10, "items": {"items": [{"item": "dowoca", "amount": 10}]}}, "updateEffect": "smeltsmoke", "category": "crafting", "idleSoundVolume": 0.5, "liquidCapacity": 10, "itemCapacity": 10, "outputLiquid": {"liquid": "molten-dowoca", "amount": 8}}