{"type": "DoubleTurret", "name": "faqymu turret", "description": ",,,", "health": 248, "size": 2, "reload": 10, "range": 207, "innacuracy": 5, "rotatespeed": 229, "ammo": {"faqymu": {"speed": 26, "damage": 52, "bulletWidth": 10, "bulletHeight": 20, "shootEffect": "shootSmall", "smokeEffect": "shootPyraFlame", "ammoMultiplier": 1}, "copper": {"speed": 31, "damage": 4, "bulletWidth": 10, "bulletHeight": 20, "shootEffect": "shootSmall", "smokeEffect": "shootPyraFlame", "ammoMultiplier": 1}, "bybity": {"speed": 1, "damage": 8, "bulletWidth": 10, "bulletHeight": 20, "shootEffect": "shootSmall", "smokeEffect": "shootPyraFlame", "ammoMultiplier": 1}}, "requirements": [{"item": "faqymu", "amount": 1}, {"item": "lead", "amount": 50}, {"item": "heruru", "amount": 41}], "category": "turret", "research": "faqymu-factory", "ammoUseEffect": "shellEjectSmall"}