{"type": "GenericCrafter", "name": "fopuru factory", "description": "...", "health": 168, "size": 2, "requirements": [{"item": "lave", "amount": 19}, {"item": "hiwenium", "amount": 2}, {"item": "yeby", "amount": 8}], "research": "mechanical-drill", "hasPower": true, "hasItems": true, "hasLiquids": true, "craftTime": 10, "consumes": {"power": 10.0, "items": {"items": [{"item": "byfyge", "amount": 7}]}, "liquid": {"liquid": "molten-jigame", "amount": 2}}, "updateEffect": "smeltsmoke", "category": "crafting", "idleSoundVolume": 0.5, "liquidCapacity": 10, "itemCapacity": 20, "outputItem": {"item": "fopuru", "amount": 4}}