{"type": "GenericSmelter", "name": "fote smelter", "description": "...", "health": 100, "size": 2, "requirements": [{"item": "motaty", "amount": 15}, {"item": "migy", "amount": 11}, {"item": "rocihy", "amount": 8}], "research": "fote-factory", "hasPower": true, "hasItems": true, "hasLiquids": true, "craftTime": 1, "consumes": {"power": 5, "items": {"items": [{"item": "fote", "amount": 10}]}}, "updateEffect": "smeltsmoke", "category": "crafting", "idleSoundVolume": 0.5, "liquidCapacity": 10, "itemCapacity": 10, "outputLiquid": {"liquid": "molten-fote", "amount": 6}}