{"type": "DoubleTurret", "name": "fydyvenium turret", "description": ",,,", "health": 290, "size": 1, "reload": 8, "range": 184, "innacuracy": 2, "rotatespeed": 187, "ammo": {"fydyvenium": {"speed": 46, "damage": 9, "bulletWidth": 10, "bulletHeight": 20, "shootEffect": "shootSmall", "smokeEffect": "shootPyraFlame", "ammoMultiplier": 1}, "divi": {"speed": 71, "damage": 16, "bulletWidth": 10, "bulletHeight": 20, "shootEffect": "shootSmall", "smokeEffect": "shootPyraFlame", "ammoMultiplier": 1}, "mahyby": {"speed": 71, "damage": 37, "bulletWidth": 10, "bulletHeight": 20, "shootEffect": "shootSmall", "smokeEffect": "shootPyraFlame", "ammoMultiplier": 1}}, "requirements": [{"item": "fydyvenium", "amount": 1}, {"item": "tumewe", "amount": 21}, {"item": "lyxele", "amount": 32}], "category": "turret", "research": "fydyvenium-factory", "ammoUseEffect": "shellEjectSmall"}