{"type": "DoubleTurret", "name": "gapa turret", "description": ",,,", "health": 231, "size": 4, "reload": 1, "range": 229, "innacuracy": 6, "rotatespeed": 114, "ammo": {"gapa": {"speed": 77, "damage": 14, "bulletWidth": 10, "bulletHeight": 20, "shootEffect": "shootSmall", "smokeEffect": "shootPyraFlame", "ammoMultiplier": 1}, "xelu": {"speed": 51, "damage": 6, "bulletWidth": 10, "bulletHeight": 20, "shootEffect": "shootSmall", "smokeEffect": "shootPyraFlame", "ammoMultiplier": 1}, "xogy": {"speed": 29, "damage": 9, "bulletWidth": 10, "bulletHeight": 20, "shootEffect": "shootSmall", "smokeEffect": "shootPyraFlame", "ammoMultiplier": 1}}, "requirements": [{"item": "gapa", "amount": 1}, {"item": "dowy", "amount": 30}, {"item": "gone", "amount": 44}], "category": "turret", "research": "gapa-factory", "ammoUseEffect": "shellEjectSmall"}