{"type": "GenericCrafter", "name": "gimy factory", "description": "...", "health": 219, "size": 2, "requirements": [{"item": "yuly", "amount": 7}, {"item": "zuzequ", "amount": 3}, {"item": "kubi", "amount": 19}], "research": "mechanical-drill", "hasPower": true, "hasItems": true, "hasLiquids": false, "craftTime": 10, "consumes": {"power": 5.0, "items": {"items": [{"item": "feyyqe", "amount": 6}, {"item": "tujy", "amount": 2}]}}, "updateEffect": "smeltsmoke", "category": "crafting", "idleSoundVolume": 0.5, "itemCapacity": 20, "outputItem": {"item": "gimy", "amount": 19}}