{"type": "GenericSmelter", "name": "gurale smelter", "description": "...", "health": 100, "size": 2, "requirements": [{"item": "hotonium", "amount": 4}, {"item": "daye", "amount": 11}, {"item": "buru", "amount": 8}], "research": "gurale-factory", "hasPower": true, "hasItems": true, "hasLiquids": true, "craftTime": 1, "consumes": {"power": 10, "items": {"items": [{"item": "gurale", "amount": 10}]}}, "updateEffect": "smeltsmoke", "category": "crafting", "idleSoundVolume": 0.5, "liquidCapacity": 10, "itemCapacity": 10, "outputLiquid": {"liquid": "molten-gurale", "amount": 10}}