{"type": "GenericCrafter", "name": "hise factory", "description": "...", "health": 210, "size": 3, "requirements": [{"item": "resenium", "amount": 14}, {"item": "togygi", "amount": 7}, {"item": "qowepa", "amount": 13}], "research": "mechanical-drill", "hasPower": true, "hasItems": true, "hasLiquids": false, "craftTime": 10, "consumes": {"power": 8.0, "items": {"items": [{"item": "sylunium", "amount": 11}, {"item": "pupyku", "amount": 1}]}}, "updateEffect": "smeltsmoke", "category": "crafting", "idleSoundVolume": 0.5, "itemCapacity": 20, "outputItem": {"item": "hise", "amount": 9}}