{"type": "GenericCrafter", "name": "hofa factory", "description": "...", "health": 358, "size": 3, "requirements": [{"item": "xype", "amount": 4}, {"item": "rajubanium", "amount": 16}, {"item": "gyfeca", "amount": 16}], "research": "mechanical-drill", "hasPower": true, "hasItems": true, "hasLiquids": false, "craftTime": 10, "consumes": {"power": 1.0, "items": {"items": [{"item": "kubi", "amount": 20}, {"item": "sibewe", "amount": 1}]}}, "updateEffect": "smeltsmoke", "category": "crafting", "idleSoundVolume": 0.5, "itemCapacity": 20, "outputItem": {"item": "hofa", "amount": 12}}