{"type": "GenericCrafter", "name": "jetuwe factory", "description": "...", "health": 429, "size": 2, "requirements": [{"item": "wohunium", "amount": 20}, {"item": "naku", "amount": 5}, {"item": "fote", "amount": 14}], "research": "mechanical-drill", "hasPower": true, "hasItems": true, "hasLiquids": true, "craftTime": 10, "consumes": {"power": 1.0, "items": {"items": [{"item": "nyyonium", "amount": 20}]}, "liquid": {"liquid": "molten-zoxi", "amount": 9}}, "updateEffect": "smeltsmoke", "category": "crafting", "idleSoundVolume": 0.5, "liquidCapacity": 10, "itemCapacity": 20, "outputItem": {"item": "jetuwe", "amount": 17}}