{"type": "GenericSmelter", "name": "jifilo smelter", "description": "...", "health": 100, "size": 2, "requirements": [{"item": "cesewo", "amount": 8}, {"item": "bore", "amount": 17}, {"item": "tisi", "amount": 8}], "research": "jifilo-factory", "hasPower": true, "hasItems": true, "hasLiquids": true, "craftTime": 1, "consumes": {"power": 7, "items": {"items": [{"item": "jifilo", "amount": 4}]}}, "updateEffect": "smeltsmoke", "category": "crafting", "idleSoundVolume": 0.5, "liquidCapacity": 10, "itemCapacity": 10, "outputLiquid": {"liquid": "molten-jifilo", "amount": 6}}