{"type": "GenericSmelter", "name": "jobo smelter", "description": "...", "health": 100, "size": 2, "requirements": [{"item": "xutire", "amount": 3}, {"item": "qebu", "amount": 6}, {"item": "fuxo", "amount": 1}], "research": "jobo-factory", "hasPower": true, "hasItems": true, "hasLiquids": true, "craftTime": 1, "consumes": {"power": 2, "items": {"items": [{"item": "jobo", "amount": 9}]}}, "updateEffect": "smeltsmoke", "category": "crafting", "idleSoundVolume": 0.5, "liquidCapacity": 10, "itemCapacity": 10, "outputLiquid": {"liquid": "molten-jobo", "amount": 2}}