{"type": "GenericSmelter", "name": "kacoju smelter", "description": "...", "health": 100, "size": 2, "requirements": [{"item": "cuba", "amount": 18}, {"item": "gumyra", "amount": 16}, {"item": "papo", "amount": 6}], "research": "kacoju-factory", "hasPower": true, "hasItems": true, "hasLiquids": true, "craftTime": 1, "consumes": {"power": 5, "items": {"items": [{"item": "kacoju", "amount": 6}]}}, "updateEffect": "smeltsmoke", "category": "crafting", "idleSoundVolume": 0.5, "liquidCapacity": 10, "itemCapacity": 10, "outputLiquid": {"liquid": "molten-kacoju", "amount": 2}}