{"type": "GenericCrafter", "name": "kexebinium factory", "description": "...", "health": 515, "size": 3, "requirements": [{"item": "xega", "amount": 17}, {"item": "mibyzo", "amount": 7}, {"item": "rexo", "amount": 19}], "research": "mechanical-drill", "hasPower": true, "hasItems": true, "hasLiquids": false, "craftTime": 10, "consumes": {"power": 2.0, "items": {"items": [{"item": "mebu", "amount": 14}, {"item": "qoki", "amount": 2}]}}, "updateEffect": "smeltsmoke", "category": "crafting", "idleSoundVolume": 0.5, "itemCapacity": 20, "outputItem": {"item": "kexebinium", "amount": 9}}