{"type": "GenericSmelter", "name": "kilu smelter", "description": "...", "health": 100, "size": 2, "requirements": [{"item": "hymonium", "amount": 14}, {"item": "vakyxinium", "amount": 2}, {"item": "wavoli", "amount": 10}], "research": "kilu-factory", "hasPower": true, "hasItems": true, "hasLiquids": true, "craftTime": 1, "consumes": {"power": 3, "items": {"items": [{"item": "kilu", "amount": 9}]}}, "updateEffect": "smeltsmoke", "category": "crafting", "idleSoundVolume": 0.5, "liquidCapacity": 10, "itemCapacity": 10, "outputLiquid": {"liquid": "molten-kilu", "amount": 3}}