{"type": "GenericSmelter", "name": "kixo smelter", "description": "...", "health": 100, "size": 2, "requirements": [{"item": "lynulo", "amount": 16}, {"item": "ruvudo", "amount": 11}, {"item": "wujifi", "amount": 5}], "research": "kixo-factory", "hasPower": true, "hasItems": true, "hasLiquids": true, "craftTime": 1, "consumes": {"power": 2, "items": {"items": [{"item": "kixo", "amount": 10}]}}, "updateEffect": "smeltsmoke", "category": "crafting", "idleSoundVolume": 0.5, "liquidCapacity": 10, "itemCapacity": 10, "outputLiquid": {"liquid": "molten-kixo", "amount": 7}}