{"type": "GenericSmelter", "name": "kocy smelter", "description": "...", "health": 100, "size": 2, "requirements": [{"item": "gahy", "amount": 9}, {"item": "maqapy", "amount": 2}, {"item": "citygo", "amount": 8}], "research": "kocy-factory", "hasPower": true, "hasItems": true, "hasLiquids": true, "craftTime": 1, "consumes": {"power": 5, "items": {"items": [{"item": "kocy", "amount": 4}]}}, "updateEffect": "smeltsmoke", "category": "crafting", "idleSoundVolume": 0.5, "liquidCapacity": 10, "itemCapacity": 10, "outputLiquid": {"liquid": "molten-kocy", "amount": 4}}