{"type": "GenericSmelter", "name": "limo smelter", "description": "...", "health": 100, "size": 2, "requirements": [{"item": "yocoke", "amount": 4}, {"item": "surge-alloy", "amount": 6}, {"item": "lynyyi", "amount": 6}], "research": "limo-factory", "hasPower": true, "hasItems": true, "hasLiquids": true, "craftTime": 1, "consumes": {"power": 2, "items": {"items": [{"item": "limo", "amount": 4}]}}, "updateEffect": "smeltsmoke", "category": "crafting", "idleSoundVolume": 0.5, "liquidCapacity": 10, "itemCapacity": 10, "outputLiquid": {"liquid": "molten-limo", "amount": 2}}