{"type": "GenericSmelter", "name": "liqy smelter", "description": "...", "health": 100, "size": 2, "requirements": [{"item": "xuricy", "amount": 17}, {"item": "salojanium", "amount": 11}, {"item": "sudu", "amount": 7}], "research": "liqy-factory", "hasPower": true, "hasItems": true, "hasLiquids": true, "craftTime": 1, "consumes": {"power": 1, "items": {"items": [{"item": "liqy", "amount": 5}]}}, "updateEffect": "smeltsmoke", "category": "crafting", "idleSoundVolume": 0.5, "liquidCapacity": 10, "itemCapacity": 10, "outputLiquid": {"liquid": "molten-liqy", "amount": 7}}