{"type": "GenericCrafter", "name": "lowapo factory", "description": "...", "health": 125, "size": 3, "requirements": [{"item": "biqa", "amount": 6}, {"item": "qimose", "amount": 17}, {"item": "byfa", "amount": 13}], "research": "mechanical-drill", "hasPower": true, "hasItems": true, "hasLiquids": false, "craftTime": 10, "consumes": {"power": 4.0, "items": {"items": [{"item": "fytuve", "amount": 11}, {"item": "gyhecu", "amount": 2}]}}, "updateEffect": "smeltsmoke", "category": "crafting", "idleSoundVolume": 0.5, "itemCapacity": 20, "outputItem": {"item": "lowapo", "amount": 12}}