{"type": "GenericCrafter", "name": "luyy factory", "description": "...", "health": 542, "size": 1, "requirements": [{"item": "bedi", "amount": 9}, {"item": "mika", "amount": 7}, {"item": "mutevi", "amount": 11}], "research": "mechanical-drill", "hasPower": true, "hasItems": true, "hasLiquids": false, "craftTime": 10, "consumes": {"power": 2.0, "items": {"items": [{"item": "piwu", "amount": 20}, {"item": "pavanium", "amount": 2}]}}, "updateEffect": "smeltsmoke", "category": "crafting", "idleSoundVolume": 0.5, "itemCapacity": 20, "outputItem": {"item": "luyy", "amount": 11}}