{"type": "GenericCrafter", "name": "mififi factory", "description": "...", "health": 278, "size": 1, "requirements": [{"item": "mivoky", "amount": 16}, {"item": "hocode", "amount": 2}, {"item": "donuba", "amount": 10}], "research": "mechanical-drill", "hasPower": true, "hasItems": true, "hasLiquids": false, "craftTime": 10, "consumes": {"power": 7.0, "items": {"items": [{"item": "lokybe", "amount": 16}, {"item": "wupera", "amount": 1}]}}, "updateEffect": "smeltsmoke", "category": "crafting", "idleSoundVolume": 0.5, "itemCapacity": 20, "outputItem": {"item": "mififi", "amount": 10}}