{"type": "GenericCrafter", "name": "negi factory", "description": "...", "health": 337, "size": 2, "requirements": [{"item": "boqi", "amount": 2}, {"item": "tisi", "amount": 4}, {"item": "kujodo", "amount": 18}], "research": "mechanical-drill", "hasPower": true, "hasItems": true, "hasLiquids": false, "craftTime": 10, "consumes": {"power": 1.0, "items": {"items": [{"item": "vojenium", "amount": 16}, {"item": "yedunium", "amount": 2}]}}, "updateEffect": "smeltsmoke", "category": "crafting", "idleSoundVolume": 0.5, "itemCapacity": 20, "outputItem": {"item": "negi", "amount": 14}}