{"type": "GenericCrafter", "name": "neni factory", "description": "...", "health": 352, "size": 2, "requirements": [{"item": "bebexu", "amount": 11}, {"item": "dutohu", "amount": 16}, {"item": "hymafa", "amount": 1}], "research": "mechanical-drill", "hasPower": true, "hasItems": true, "hasLiquids": true, "craftTime": 10, "consumes": {"power": 4.0, "items": {"items": [{"item": "vyse", "amount": 18}]}, "liquid": {"liquid": "molten-xapu", "amount": 7}}, "updateEffect": "smeltsmoke", "category": "crafting", "idleSoundVolume": 0.5, "liquidCapacity": 10, "itemCapacity": 20, "outputItem": {"item": "neni", "amount": 10}}