{"type": "GenericCrafter", "name": "netito factory", "description": "...", "health": 282, "size": 2, "requirements": [{"item": "cidenium", "amount": 6}, {"item": "todenium", "amount": 1}, {"item": "hite", "amount": 6}], "research": "mechanical-drill", "hasPower": true, "hasItems": true, "hasLiquids": true, "craftTime": 10, "consumes": {"power": 10.0, "items": {"items": [{"item": "nijunium", "amount": 11}]}, "liquid": {"liquid": "molten-zypiqi", "amount": 5}}, "updateEffect": "smeltsmoke", "category": "crafting", "idleSoundVolume": 0.5, "liquidCapacity": 10, "itemCapacity": 20, "outputItem": {"item": "netito", "amount": 1}}