{"type": "GenericCrafter", "name": "niyy factory", "description": "...", "health": 324, "size": 2, "requirements": [{"item": "xysu", "amount": 1}, {"item": "ruwysu", "amount": 18}, {"item": "kery", "amount": 5}], "research": "mechanical-drill", "hasPower": true, "hasItems": true, "hasLiquids": false, "craftTime": 10, "consumes": {"power": 9.0, "items": {"items": [{"item": "saleru", "amount": 6}, {"item": "cuwa", "amount": 2}]}}, "updateEffect": "smeltsmoke", "category": "crafting", "idleSoundVolume": 0.5, "itemCapacity": 20, "outputItem": {"item": "niyy", "amount": 20}}