{"type": "DoubleTurret", "name": "pigydinium turret", "description": ",,,", "health": 63, "size": 2, "reload": 1, "range": 210, "innacuracy": 7, "rotatespeed": 105, "ammo": {"pigydinium": {"speed": 8, "damage": 59, "bulletWidth": 10, "bulletHeight": 20, "shootEffect": "shootSmall", "smokeEffect": "shootPyraFlame", "ammoMultiplier": 1}, "rylyki": {"speed": 8, "damage": 12, "bulletWidth": 10, "bulletHeight": 20, "shootEffect": "shootSmall", "smokeEffect": "shootPyraFlame", "ammoMultiplier": 1}, "myyu": {"speed": 41, "damage": 32, "bulletWidth": 10, "bulletHeight": 20, "shootEffect": "shootSmall", "smokeEffect": "shootPyraFlame", "ammoMultiplier": 1}}, "requirements": [{"item": "pigydinium", "amount": 1}, {"item": "povazu", "amount": 30}, {"item": "ridu", "amount": 36}], "category": "turret", "research": "pigydinium-factory", "ammoUseEffect": "shellEjectSmall"}