{"type": "GenericSmelter", "name": "pyqynium smelter", "description": "...", "health": 100, "size": 2, "requirements": [{"item": "qiregynium", "amount": 9}, {"item": "miyoqu", "amount": 6}, {"item": "dugypa", "amount": 1}], "research": "pyqynium-factory", "hasPower": true, "hasItems": true, "hasLiquids": true, "craftTime": 1, "consumes": {"power": 5, "items": {"items": [{"item": "pyqynium", "amount": 10}]}}, "updateEffect": "smeltsmoke", "category": "crafting", "idleSoundVolume": 0.5, "liquidCapacity": 10, "itemCapacity": 10, "outputLiquid": {"liquid": "molten-pyqynium", "amount": 4}}