{"type": "GenericSmelter", "name": "qefi smelter", "description": "...", "health": 100, "size": 2, "requirements": [{"item": "qobu", "amount": 5}, {"item": "vubedi", "amount": 10}, {"item": "heke", "amount": 1}], "research": "qefi-factory", "hasPower": true, "hasItems": true, "hasLiquids": true, "craftTime": 1, "consumes": {"power": 4, "items": {"items": [{"item": "qefi", "amount": 10}]}}, "updateEffect": "smeltsmoke", "category": "crafting", "idleSoundVolume": 0.5, "liquidCapacity": 10, "itemCapacity": 10, "outputLiquid": {"liquid": "molten-qefi", "amount": 3}}