{"type": "GenericSmelter", "name": "qejaba smelter", "description": "...", "health": 100, "size": 2, "requirements": [{"item": "pyqynium", "amount": 11}, {"item": "zexi", "amount": 7}, {"item": "tatavo", "amount": 7}], "research": "qejaba-factory", "hasPower": true, "hasItems": true, "hasLiquids": true, "craftTime": 1, "consumes": {"power": 5, "items": {"items": [{"item": "qejaba", "amount": 3}]}}, "updateEffect": "smeltsmoke", "category": "crafting", "idleSoundVolume": 0.5, "liquidCapacity": 10, "itemCapacity": 10, "outputLiquid": {"liquid": "molten-qejaba", "amount": 4}}