{"type": "GenericCrafter", "name": "qiye factory", "description": "...", "health": 274, "size": 3, "requirements": [{"item": "jewa", "amount": 12}, {"item": "qeca", "amount": 5}, {"item": "pufere", "amount": 9}], "research": "mechanical-drill", "hasPower": true, "hasItems": true, "hasLiquids": true, "craftTime": 10, "consumes": {"power": 3.0, "items": {"items": [{"item": "siwi", "amount": 19}]}, "liquid": {"liquid": "molten-xoxu", "amount": 10}}, "updateEffect": "smeltsmoke", "category": "crafting", "idleSoundVolume": 0.5, "liquidCapacity": 10, "itemCapacity": 20, "outputItem": {"item": "qiye", "amount": 20}}