{"type": "GenericCrafter", "name": "qyyudi factory", "description": "...", "health": 213, "size": 3, "requirements": [{"item": "gaxunium", "amount": 8}, {"item": "purunium", "amount": 10}, {"item": "huniji", "amount": 9}], "research": "mechanical-drill", "hasPower": true, "hasItems": true, "hasLiquids": true, "craftTime": 10, "consumes": {"power": 9.0, "items": {"items": [{"item": "hozivi", "amount": 15}]}, "liquid": {"liquid": "molten-lypeja", "amount": 2}}, "updateEffect": "smeltsmoke", "category": "crafting", "idleSoundVolume": 0.5, "liquidCapacity": 10, "itemCapacity": 20, "outputItem": {"item": "qyyudi", "amount": 18}}