{"type": "GenericCrafter", "name": "rahu factory", "description": "...", "health": 325, "size": 2, "requirements": [{"item": "qegynium", "amount": 9}, {"item": "nypenium", "amount": 7}, {"item": "diwyci", "amount": 20}], "research": "mechanical-drill", "hasPower": true, "hasItems": true, "hasLiquids": false, "craftTime": 10, "consumes": {"power": 7.0, "items": {"items": [{"item": "mynufu", "amount": 12}, {"item": "tivu", "amount": 2}]}}, "updateEffect": "smeltsmoke", "category": "crafting", "idleSoundVolume": 0.5, "itemCapacity": 20, "outputItem": {"item": "rahu", "amount": 9}}