{"type": "GenericCrafter", "name": "rilo factory", "description": "...", "health": 279, "size": 2, "requirements": [{"item": "kufi", "amount": 2}, {"item": "togi", "amount": 14}, {"item": "gasu", "amount": 9}], "research": "mechanical-drill", "hasPower": true, "hasItems": true, "hasLiquids": false, "craftTime": 10, "consumes": {"power": 8.0, "items": {"items": [{"item": "vega", "amount": 19}, {"item": "rajela", "amount": 2}]}}, "updateEffect": "smeltsmoke", "category": "crafting", "idleSoundVolume": 0.5, "itemCapacity": 20, "outputItem": {"item": "rilo", "amount": 6}}