{"type": "GenericSmelter", "name": "rizinium smelter", "description": "...", "health": 100, "size": 2, "requirements": [{"item": "yodary", "amount": 8}, {"item": "bily", "amount": 15}, {"item": "wana", "amount": 7}], "research": "rizinium-factory", "hasPower": true, "hasItems": true, "hasLiquids": true, "craftTime": 1, "consumes": {"power": 2, "items": {"items": [{"item": "rizinium", "amount": 5}]}}, "updateEffect": "smeltsmoke", "category": "crafting", "idleSoundVolume": 0.5, "liquidCapacity": 10, "itemCapacity": 10, "outputLiquid": {"liquid": "molten-rizinium", "amount": 6}}