{"type": "GenericCrafter", "name": "sedowe factory", "description": "...", "health": 465, "size": 2, "requirements": [{"item": "fikunium", "amount": 10}, {"item": "tiqeti", "amount": 1}, {"item": "suta", "amount": 10}], "research": "mechanical-drill", "hasPower": true, "hasItems": true, "hasLiquids": false, "craftTime": 10, "consumes": {"power": 2.0, "items": {"items": [{"item": "yeku", "amount": 3}, {"item": "yodo", "amount": 1}]}}, "updateEffect": "smeltsmoke", "category": "crafting", "idleSoundVolume": 0.5, "itemCapacity": 20, "outputItem": {"item": "sedowe", "amount": 2}}