{"type": "GenericCrafter", "name": "sevinium factory", "description": "...", "health": 509, "size": 2, "requirements": [{"item": "lobojenium", "amount": 14}, {"item": "juwynium", "amount": 17}, {"item": "luvaji", "amount": 4}], "research": "mechanical-drill", "hasPower": true, "hasItems": true, "hasLiquids": true, "craftTime": 10, "consumes": {"power": 6.0, "items": {"items": [{"item": "fulyzynium", "amount": 1}]}, "liquid": {"liquid": "molten-nufuponium", "amount": 5}}, "updateEffect": "smeltsmoke", "category": "crafting", "idleSoundVolume": 0.5, "liquidCapacity": 10, "itemCapacity": 20, "outputItem": {"item": "sevinium", "amount": 10}}