{"type": "DoubleTurret", "name": "siwi turret", "description": ",,,", "health": 369, "size": 4, "reload": 7, "range": 93, "innacuracy": 3, "rotatespeed": 222, "ammo": {"siwi": {"speed": 65, "damage": 43, "bulletWidth": 10, "bulletHeight": 20, "shootEffect": "shootSmall", "smokeEffect": "shootPyraFlame", "ammoMultiplier": 1}, "nufuponium": {"speed": 33, "damage": 46, "bulletWidth": 10, "bulletHeight": 20, "shootEffect": "shootSmall", "smokeEffect": "shootPyraFlame", "ammoMultiplier": 1}, "reju": {"speed": 49, "damage": 34, "bulletWidth": 10, "bulletHeight": 20, "shootEffect": "shootSmall", "smokeEffect": "shootPyraFlame", "ammoMultiplier": 1}}, "requirements": [{"item": "siwi", "amount": 1}, {"item": "siqefo", "amount": 47}, {"item": "giho", "amount": 38}], "category": "turret", "research": "siwi-factory", "ammoUseEffect": "shellEjectSmall"}