{"type": "GenericCrafter", "name": "suvi factory", "description": "...", "health": 214, "size": 2, "requirements": [{"item": "zeva", "amount": 16}, {"item": "fobige", "amount": 11}, {"item": "wiba", "amount": 17}], "research": "mechanical-drill", "hasPower": true, "hasItems": true, "hasLiquids": false, "craftTime": 10, "consumes": {"power": 6.0, "items": {"items": [{"item": "loja", "amount": 10}, {"item": "pojesu", "amount": 2}]}}, "updateEffect": "smeltsmoke", "category": "crafting", "idleSoundVolume": 0.5, "itemCapacity": 20, "outputItem": {"item": "suvi", "amount": 15}}