{"type": "GenericCrafter", "name": "sycexi factory", "description": "...", "health": 147, "size": 3, "requirements": [{"item": "marici", "amount": 17}, {"item": "yypunium", "amount": 14}, {"item": "pezale", "amount": 3}], "research": "mechanical-drill", "hasPower": true, "hasItems": true, "hasLiquids": false, "craftTime": 10, "consumes": {"power": 2.0, "items": {"items": [{"item": "reboka", "amount": 19}, {"item": "sawy", "amount": 1}]}}, "updateEffect": "smeltsmoke", "category": "crafting", "idleSoundVolume": 0.5, "itemCapacity": 20, "outputItem": {"item": "sycexi", "amount": 20}}