{"type": "DoubleTurret", "name": "syqi turret", "description": ",,,", "health": 139, "size": 2, "reload": 4, "range": 360, "innacuracy": 5, "rotatespeed": 167, "ammo": {"syqi": {"speed": 36, "damage": 46, "bulletWidth": 10, "bulletHeight": 20, "shootEffect": "shootSmall", "smokeEffect": "shootPyraFlame", "ammoMultiplier": 1}, "tasusynium": {"speed": 13, "damage": 59, "bulletWidth": 10, "bulletHeight": 20, "shootEffect": "shootSmall", "smokeEffect": "shootPyraFlame", "ammoMultiplier": 1}, "hocona": {"speed": 64, "damage": 47, "bulletWidth": 10, "bulletHeight": 20, "shootEffect": "shootSmall", "smokeEffect": "shootPyraFlame", "ammoMultiplier": 1}}, "requirements": [{"item": "syqi", "amount": 1}, {"item": "kagopy", "amount": 23}, {"item": "yowoje", "amount": 27}], "category": "turret", "research": "syqi-factory", "ammoUseEffect": "shellEjectSmall"}