{"type": "GenericCrafter", "name": "tedi factory", "description": "...", "health": 557, "size": 3, "requirements": [{"item": "hufema", "amount": 6}, {"item": "yytiye", "amount": 13}, {"item": "kubi", "amount": 4}], "research": "mechanical-drill", "hasPower": true, "hasItems": true, "hasLiquids": false, "craftTime": 10, "consumes": {"power": 9.0, "items": {"items": [{"item": "lead", "amount": 19}, {"item": "kefy", "amount": 2}]}}, "updateEffect": "smeltsmoke", "category": "crafting", "idleSoundVolume": 0.5, "itemCapacity": 20, "outputItem": {"item": "tedi", "amount": 16}}