{"type": "GenericCrafter", "name": "tiyajo factory", "description": "...", "health": 477, "size": 2, "requirements": [{"item": "pymu", "amount": 18}, {"item": "hobo", "amount": 14}, {"item": "qari", "amount": 2}], "research": "mechanical-drill", "hasPower": true, "hasItems": true, "hasLiquids": false, "craftTime": 10, "consumes": {"power": 2.0, "items": {"items": [{"item": "qipy", "amount": 11}, {"item": "wupa", "amount": 2}]}}, "updateEffect": "smeltsmoke", "category": "crafting", "idleSoundVolume": 0.5, "itemCapacity": 20, "outputItem": {"item": "tiyajo", "amount": 2}}