{"type": "DoubleTurret", "name": "totiji turret", "description": ",,,", "health": 185, "size": 1, "reload": 2, "range": 108, "innacuracy": 3, "rotatespeed": 63, "ammo": {"totiji": {"speed": 30, "damage": 26, "bulletWidth": 10, "bulletHeight": 20, "shootEffect": "shootSmall", "smokeEffect": "shootPyraFlame", "ammoMultiplier": 1}, "xidunium": {"speed": 63, "damage": 30, "bulletWidth": 10, "bulletHeight": 20, "shootEffect": "shootSmall", "smokeEffect": "shootPyraFlame", "ammoMultiplier": 1}, "higyhy": {"speed": 93, "damage": 45, "bulletWidth": 10, "bulletHeight": 20, "shootEffect": "shootSmall", "smokeEffect": "shootPyraFlame", "ammoMultiplier": 1}}, "requirements": [{"item": "totiji", "amount": 1}, {"item": "gyza", "amount": 43}, {"item": "caxoni", "amount": 45}], "category": "turret", "research": "totiji-factory", "ammoUseEffect": "shellEjectSmall"}