{"type": "GenericCrafter", "name": "tyjy factory", "description": "...", "health": 211, "size": 1, "requirements": [{"item": "nedybu", "amount": 14}, {"item": "boko", "amount": 5}, {"item": "sybo", "amount": 2}], "research": "mechanical-drill", "hasPower": true, "hasItems": true, "hasLiquids": true, "craftTime": 10, "consumes": {"power": 3.0, "items": {"items": [{"item": "buco", "amount": 8}]}, "liquid": {"liquid": "molten-mytati", "amount": 6}}, "updateEffect": "smeltsmoke", "category": "crafting", "idleSoundVolume": 0.5, "liquidCapacity": 10, "itemCapacity": 20, "outputItem": {"item": "tyjy", "amount": 11}}