{"type": "DoubleTurret", "name": "vakyxinium turret", "description": ",,,", "health": 87, "size": 2, "reload": 3, "range": 126, "innacuracy": 8, "rotatespeed": 284, "ammo": {"vakyxinium": {"speed": 52, "damage": 41, "bulletWidth": 10, "bulletHeight": 20, "shootEffect": "shootSmall", "smokeEffect": "shootPyraFlame", "ammoMultiplier": 1}, "wiba": {"speed": 12, "damage": 43, "bulletWidth": 10, "bulletHeight": 20, "shootEffect": "shootSmall", "smokeEffect": "shootPyraFlame", "ammoMultiplier": 1}, "fogodo": {"speed": 52, "damage": 59, "bulletWidth": 10, "bulletHeight": 20, "shootEffect": "shootSmall", "smokeEffect": "shootPyraFlame", "ammoMultiplier": 1}}, "requirements": [{"item": "vakyxinium", "amount": 1}, {"item": "tuxu", "amount": 49}, {"item": "thorium", "amount": 19}], "category": "turret", "research": "vakyxinium-factory", "ammoUseEffect": "shellEjectSmall"}