{"type": "GenericCrafter", "name": "vigyqinium factory", "description": "...", "health": 199, "size": 2, "requirements": [{"item": "bihu", "amount": 20}, {"item": "hofa", "amount": 6}, {"item": "guvoja", "amount": 4}], "research": "mechanical-drill", "hasPower": true, "hasItems": true, "hasLiquids": false, "craftTime": 10, "consumes": {"power": 9.0, "items": {"items": [{"item": "basomi", "amount": 20}, {"item": "pele", "amount": 2}]}}, "updateEffect": "smeltsmoke", "category": "crafting", "idleSoundVolume": 0.5, "itemCapacity": 20, "outputItem": {"item": "vigyqinium", "amount": 15}}