{"type": "GenericCrafter", "name": "vody factory", "description": "...", "health": 551, "size": 1, "requirements": [{"item": "wizisa", "amount": 13}, {"item": "kibanium", "amount": 1}, {"item": "pugi", "amount": 2}], "research": "mechanical-drill", "hasPower": true, "hasItems": true, "hasLiquids": true, "craftTime": 10, "consumes": {"power": 1.0, "items": {"items": [{"item": "fysubi", "amount": 18}]}, "liquid": {"liquid": "molten-womanium", "amount": 9}}, "updateEffect": "smeltsmoke", "category": "crafting", "idleSoundVolume": 0.5, "liquidCapacity": 10, "itemCapacity": 20, "outputItem": {"item": "vody", "amount": 16}}