{"type": "GenericCrafter", "name": "vuponium factory", "description": "...", "health": 344, "size": 2, "requirements": [{"item": "zoyinium", "amount": 13}, {"item": "xuzy", "amount": 19}, {"item": "zadyle", "amount": 7}], "research": "mechanical-drill", "hasPower": true, "hasItems": true, "hasLiquids": true, "craftTime": 10, "consumes": {"power": 4.0, "items": {"items": [{"item": "zyfita", "amount": 15}]}, "liquid": {"liquid": "molten-bakiyy", "amount": 4}}, "updateEffect": "smeltsmoke", "category": "crafting", "idleSoundVolume": 0.5, "liquidCapacity": 10, "itemCapacity": 20, "outputItem": {"item": "vuponium", "amount": 19}}