{"type": "GenericCrafter", "name": "wivo factory", "description": "...", "health": 500, "size": 2, "requirements": [{"item": "cotyyo", "amount": 4}, {"item": "tozokinium", "amount": 8}, {"item": "vyjoti", "amount": 20}], "research": "mechanical-drill", "hasPower": true, "hasItems": true, "hasLiquids": false, "craftTime": 10, "consumes": {"power": 4.0, "items": {"items": [{"item": "hitiva", "amount": 4}, {"item": "haxi", "amount": 1}]}}, "updateEffect": "smeltsmoke", "category": "crafting", "idleSoundVolume": 0.5, "itemCapacity": 20, "outputItem": {"item": "wivo", "amount": 5}}