{"type": "GenericCrafter", "name": "xobasonium factory", "description": "...", "health": 513, "size": 2, "requirements": [{"item": "bube", "amount": 1}, {"item": "fupymi", "amount": 17}, {"item": "yyxafo", "amount": 16}], "research": "mechanical-drill", "hasPower": true, "hasItems": true, "hasLiquids": false, "craftTime": 10, "consumes": {"power": 1.0, "items": {"items": [{"item": "bavivo", "amount": 6}, {"item": "woyu", "amount": 2}]}}, "updateEffect": "smeltsmoke", "category": "crafting", "idleSoundVolume": 0.5, "itemCapacity": 20, "outputItem": {"item": "xobasonium", "amount": 7}}