{"type": "GenericCrafter", "name": "xuvogi factory", "description": "...", "health": 442, "size": 1, "requirements": [{"item": "xuqi", "amount": 20}, {"item": "muti", "amount": 14}, {"item": "jazu", "amount": 3}], "research": "mechanical-drill", "hasPower": true, "hasItems": true, "hasLiquids": true, "craftTime": 10, "consumes": {"power": 8.0, "items": {"items": [{"item": "cywiwa", "amount": 20}]}, "liquid": {"liquid": "molten-gyporu", "amount": 5}}, "updateEffect": "smeltsmoke", "category": "crafting", "idleSoundVolume": 0.5, "liquidCapacity": 10, "itemCapacity": 20, "outputItem": {"item": "xuvogi", "amount": 18}}