{"type": "GenericCrafter", "name": "yuvarynium factory", "description": "...", "health": 165, "size": 2, "requirements": [{"item": "buli", "amount": 14}, {"item": "teza", "amount": 2}, {"item": "kado", "amount": 18}], "research": "mechanical-drill", "hasPower": true, "hasItems": true, "hasLiquids": true, "craftTime": 10, "consumes": {"power": 2.0, "items": {"items": [{"item": "judeconium", "amount": 15}]}, "liquid": {"liquid": "molten-goxize", "amount": 7}}, "updateEffect": "smeltsmoke", "category": "crafting", "idleSoundVolume": 0.5, "liquidCapacity": 10, "itemCapacity": 20, "outputItem": {"item": "yuvarynium", "amount": 12}}