{"type": "GenericCrafter", "name": "yuwo factory", "description": "...", "health": 405, "size": 1, "requirements": [{"item": "jaga", "amount": 4}, {"item": "niyi", "amount": 18}, {"item": "bebofo", "amount": 7}], "research": "mechanical-drill", "hasPower": true, "hasItems": true, "hasLiquids": false, "craftTime": 10, "consumes": {"power": 2.0, "items": {"items": [{"item": "togygi", "amount": 5}, {"item": "byyu", "amount": 2}]}}, "updateEffect": "smeltsmoke", "category": "crafting", "idleSoundVolume": 0.5, "itemCapacity": 20, "outputItem": {"item": "yuwo", "amount": 9}}