{"type": "GenericSmelter", "name": "yyludunium smelter", "description": "...", "health": 100, "size": 2, "requirements": [{"item": "fepiva", "amount": 17}, {"item": "xyko", "amount": 10}, {"item": "gygi", "amount": 10}], "research": "yyludunium-factory", "hasPower": true, "hasItems": true, "hasLiquids": true, "craftTime": 1, "consumes": {"power": 7, "items": {"items": [{"item": "yyludunium", "amount": 7}]}}, "updateEffect": "smeltsmoke", "category": "crafting", "idleSoundVolume": 0.5, "liquidCapacity": 10, "itemCapacity": 10, "outputLiquid": {"liquid": "molten-yyludunium", "amount": 4}}