{"type": "GenericCrafter", "name": "zowanium factory", "description": "...", "health": 333, "size": 1, "requirements": [{"item": "nimi", "amount": 10}, {"item": "tayi", "amount": 17}, {"item": "tozuza", "amount": 3}], "research": "mechanical-drill", "hasPower": true, "hasItems": true, "hasLiquids": false, "craftTime": 10, "consumes": {"power": 10.0, "items": {"items": [{"item": "hocode", "amount": 17}, {"item": "gineta", "amount": 1}]}}, "updateEffect": "smeltsmoke", "category": "crafting", "idleSoundVolume": 0.5, "itemCapacity": 20, "outputItem": {"item": "zowanium", "amount": 12}}