{"type": "GenericSmelter", "name": "zyru smelter", "description": "...", "health": 100, "size": 2, "requirements": [{"item": "muby", "amount": 17}, {"item": "kide", "amount": 18}, {"item": "cuhynenium", "amount": 5}], "research": "zyru-factory", "hasPower": true, "hasItems": true, "hasLiquids": true, "craftTime": 1, "consumes": {"power": 3, "items": {"items": [{"item": "zyru", "amount": 4}]}}, "updateEffect": "smeltsmoke", "category": "crafting", "idleSoundVolume": 0.5, "liquidCapacity": 10, "itemCapacity": 10, "outputLiquid": {"liquid": "molten-zyru", "amount": 2}}